saksham_bt_ind/__init__.py
saksham_bt_ind/bollinger/__init__.py
saksham_bt_ind/bollinger/bollingerbandwidth.py
saksham_bt_ind-0.2.dist-info/METADATA
saksham_bt_ind-0.2.dist-info/WHEEL
saksham_bt_ind-0.2.dist-info/top_level.txt
saksham_bt_ind-0.2.dist-info/RECORD
