Metadata-Version: 2.1
Name: saksham-bt-ind
Version: 0.2
Summary: A Python Library of indicators (based on backtrader) commonly used in technical analysis while Trading in Financial markets.
Home-page: UNKNOWN
Author: SAKSHAM (Platform powered by Finnovesh Incorporation)
Author-email: <finnovesh@gmail.com>
License: UNKNOWN
Keywords: python,keygennerator,keygen,password
Platform: UNKNOWN
Classifier: Development Status :: 1 - Planning
Classifier: Intended Audience :: Developers
Classifier: Programming Language :: Python :: 3
Classifier: Operating System :: Unix
Classifier: Operating System :: MacOS :: MacOS X
Classifier: Operating System :: Microsoft :: Windows
Requires-Dist: backtrader
